RunNotebook/__init__.py
RunNotebook/notebook_sphinxext.py
RunNotebook/notebookcell_sphinxext.py
RunNotebook-0.3.1.dist-info/METADATA
RunNotebook-0.3.1.dist-info/RECORD
RunNotebook-0.3.1.dist-info/WHEEL
RunNotebook-0.3.1.dist-info/top_level.txt
