Metadata-Version: 2.1
Name: RunNotebook
Version: 0.3.1
Summary: UNKNOWN
Home-page: https://github.com/ngoldbaum/RunNotebook
Author: Nathan Goldbaum
Author-email: nathan12343@gmail.com
License: UNKNOWN
Platform: UNKNOWN
Requires-Dist: sphinx
Requires-Dist: jupyter
Requires-Dist: nbconvert
Requires-Dist: nbformat
